habcatev/__init__.py
habcatev/__main__.py
habcatev/common/__init__.py
habcatev/common/logging.py
habcatev/common/logs.py
habcatev/device/Device.py
habcatev/device/MQTTClient.py
habcatev/device/__init__.py
habcatev-0.0.4.dist-info/LICENSE.txt
habcatev-0.0.4.dist-info/METADATA
habcatev-0.0.4.dist-info/WHEEL
habcatev-0.0.4.dist-info/top_level.txt
habcatev-0.0.4.dist-info/RECORD
