Metadata-Version: 2.1
Name: habcatev
Version: 0.0.4
Summary: Librería para la gestión de eventos
Home-page: https://github.com/alpeza/habcatev
Author: HabCat Team
Author-email: 
License: UNKNOWN
Platform: UNKNOWN
Classifier: Programming Language :: Python :: 3
Classifier: License :: OSI Approved :: MIT License
Classifier: Operating System :: OS Independent
Requires-Dist: paho-mqtt (==1.5.1)
Requires-Dist: PyYAML (==5.4.1)
